[
  {
    "user_id": "user_1",
    "personagens": {},
    "sets_completos": []
  },
  {
    "user_id": 1,
    "personagens": {
      "domina_comum": 5,
      "wrecking_ball_comum": 14,
      "brigitte_comum": 12,
      "lifeweaver_comum": 9,
      "mauga_comum": 10,
      "baptiste_comum": 12,
      "capita_lacroix": 2,
      "cassidy_van_helsing": 22,
      "lifeweaver_dourado": 5,
      "ramattra_comum": 14,
      "genji_comum": 20,
      "mercy_conjuradora": 10,
      "kiriko_coracao": 14,
      "zenyatta_cultista": 16,
      "freja_comum": 13,
      "hanzo_comum": 10,
      "roadhog_comum": 7,
      "pharah_comum": 11,
      "mercy_sigrun": 14,
      "orisa_comum": 9,
      "reaper_comum": 10,
      "emre_comum": 13,
      "winston_comum": 10,
      "illari_comum": 7,
      "zenyatta_comum": 11,
      "reaper_dourado": 1,
      "cassidy_comum": 11,
      "winston_extraterreste": 11,
      "reinhardt_comum": 5,
      "echo_comum": 16,
      "venture_comum": 10,
      "sojourn_comum": 12,
      "bastion_comum": 9,
      "junkrat_comum": 8,
      "sombra_comum": 9,
      "zarya_comum": 8,
      "moira_comum": 7,
      "sigma_comum": 13,
      "anran_comum": 13,
      "genji_baihu": 16,
      "widowmaker_comum": 7,
      "widowmaker_coracao": 14,
      "freja_coracao": 13,
      "soldado_76_comum": 9,
      "mercy_diabrete": 22,
      "genji_oni": 17,
      "vendetta_comum": 9,
      "mercy_comum": 10,
      "sombra_cacadora_demonios": 18,
      "mizuki_comum": 9,
      "torbjorn_engenheiro_espacial": 12,
      "torbjorn_comum": 13,
      "rainha_junker_comum": 8,
      "rainha_junker_executora": 14,
      "symmetra_comum": 8,
      "freja_dourado": 8,
      "tracer_comum": 8,
      "mei_comum": 9,
      "brigitte_dourado": 4,
      "kiriko_comum": 12,
      "hazard_comum": 4,
      "mei_dourado": 3,
      "doomfist_comum": 5,
      "ana_comum": 8,
      "hanzo_okami": 11,
      "reinhardt_gridironhardt": 14,
      "junkrat_junkstein": 8,
      "widowmaker_cacadora": 15,
      "brigitte_coracao": 10,
      "roadhog_dourado": 5,
      "juno_comum": 6,
      "reaper_abobora": 14,
      "mizuki_dourado": 3,
      "jetpack_cat_comum": 5,
      "ashe_comum": 9,
      "hanzo_dourado": 2,
      "ramattra_poseidon": 5,
      "widowmaker_dourado": 6,
      "fera_grandeosa": 3,
      "titan_magma": 5,
      "juno_coracao": 4,
      "canhao_capsulas": 2,
      "dva_comum": 7,
      "sigma_dourado": 3,
      "vengeance": 1,
      "bastion_gwishin": 4,
      "sentinela_ultra-violeta": 2,
      "arqui-comandante_amari": 6,
      "rainha_junker_dourado": 2,
      "echo_dourado": 2,
      "libertacao": 2,
      "demonio_aprisionado": 4,
      "ana_dourado": 3,
      "talon_zarya": 7,
      "sojourn_dourado": 3,
      "bastion_dourado": 2,
      "jetpack_cat_dourado": 4,
      "imperador_galatico": 3,
      "tracer_dourado": 2,
      "operadora_oxton": 3,
      "dame_chance": 3,
      "pharah_dourado": 1,
      "comandante_ataque": 5,
      "guardia_espiritual": 2,
      "emre_dourado": 3,
      "vendetta_dourado": 3,
      "pulo_online": 5,
      "wuyang_comum": 2,
      "aventureira": 2,
      "genji_dourado": 4,
      "lucio_hermes": 3,
      "cassidy_dourado": 4,
      "lucio_dourado": 5,
      "pharah_hades": 3,
      "destruidor_z-3n": 4,
      "pistoleiro_divino": 6,
      "ocaso_flamejante": 4,
      "ramattra_dourado": 3,
      "zarya_dourado": 2,
      "junkrat_dourado": 2,
      "moira_dourado": 6,
      "wrecking_ball_dourado": 3,
      "imperatriz_calamidade": 5,
      "hazard_dourado": 1,
      "ashe_dourado": 4,
      "onryo": 2,
      "ashe_warlock": 1,
      "sol_obscuro": 3,
      "mauga_dourado": 3,
      "zenyatta_dourado": 3,
      "dva_dourado": 2,
      "echo_furtividade": 4,
      "baptiste_dourado": 3,
      "winston_dourado": 5,
      "symmetra_dourado": 1,
      "rosa_de_chumbo": 2,
      "invocadora_ancestral": 2,
      "kiriko_dourado": 2,
      "pixiu": 2,
      "ramattra_fool": 5,
      "zenyatta_fool": 5,
      "winston_fool": 7,
      "cassidy_fool": 3,
      "bastion_kishin": 1,
      "dva_chibi": 4,
      "wrecking_ball_fool": 5,
      "symmetra_fool": 2,
      "fallen_knight": 1,
      "cyber_combustivel": 2,
      "soldado_76_dourado": 2,
      "druida_divino": 2,
      "a-7000_Wargod": 2,
      "wuyang_dourado": 3,
      "lucio_comum": 3,
      "orisa_dourado": 1,
      "thor": 1,
      "zeus": 3,
      "lucio_fool": 4,
      "cyber_demonio": 3,
      "brigitte_talon": 4,
      "torbjorn_dourado": 1,
      "domina_dourado": 1,
      "horang": 1,
      "feiticeira": 2,
      "amateratsu": 1,
      "guardia_celestial": 1,
      "anubis": 2,
      "venture_dourado": 1,
      "magitecnologia_misericordiosa": 1,
      "atiradora_das_estrelas": 1,
      "sombra_dourado": 1
    },
    "sets_completos": [
      "freja",
      "roadhog",
      "melee",
      "shimada",
      "espacial",
      "talon",
      "overwatch",
      "blackwatch",
      "vishkar",
      "junkers",
      "yokai",
      "omnico",
      "cacador",
      "campeao",
      "mizuki",
      "selvagem",
      "ironclad",
      "deadlock",
      "bastion",
      "sojourn",
      "jetpack_cat",
      "sigma",
      "emre",
      "vendetta",
      "mei",
      "escola_elemental",
      "tracer",
      "guerreiro",
      "pharah",
      "cassidy",
      "ramattra",
      "fogo",
      "zarya",
      "wrecking_ball",
      "hazard",
      "hanzo",
      "mauga",
      "echo",
      "baptiste",
      "winston",
      "symmetra",
      "ashe",
      "moira",
      "zenyatta",
      "junkrat",
      "futurista",
      "lifeweaver",
      "soldado_76",
      "ana",
      "wuyang",
      "lucio",
      "classico",
      "nova_era_overwatch",
      "orisa",
      "rainha_junker",
      "panteao",
      "april_fools",
      "genji",
      "demonio",
      "brigitte",
      "mirror",
      "torbjorn",
      "domina",
      "dva",
      "meka",
      "widowmaker",
      "magica",
      "kiriko",
      "sol",
      "divino",
      "submundo",
      "mitico",
      "venture",
      "coracao",
      "sombra"
    ]
  },
  {
    "user_id": 2,
    "personagens": {
      "winston_fool": 3,
      "baptiste_comum": 1,
      "mauga_comum": 2,
      "zenyatta_cultista": 2,
      "symmetra_comum": 1,
      "torbjorn_engenheiro_espacial": 2,
      "brigitte_comum": 1,
      "illari_comum": 1,
      "widowmaker_comum": 1,
      "widowmaker_coracao": 2,
      "vendetta_comum": 2,
      "sombra_cacadora_demonios": 1,
      "reinhardt_gridironhardt": 2,
      "cassidy_comum": 3,
      "arqui-comandante_amari": 1,
      "ashe_comum": 1,
      "genji_oni": 2,
      "mercy_sigrun": 1,
      "doomfist_comum": 1,
      "venture_comum": 1,
      "lucio_comum": 1,
      "freja_coracao": 1,
      "widowmaker_cacadora": 1,
      "juno_comum": 1,
      "reinhardt_comum": 1,
      "reaper_comum": 2,
      "mizuki_dourado": 1,
      "torbjorn_dourado": 1,
      "doomfist_dourado": 1,
      "rainha_junker_comum": 1,
      "operadora_oxton": 1,
      "symmetra_fool": 2,
      "mercy_diabrete": 1,
      "hanzo_comum": 1,
      "genji_baihu": 1,
      "brigitte_coracao": 2,
      "dva_comum": 2,
      "wrecking_ball_comum": 2,
      "echo_dourado": 1,
      "domina_comum": 1,
      "zarya_comum": 1,
      "wuyang_comum": 1,
      "ramattra_comum": 1,
      "orisa_comum": 1,
      "juno_dourado": 1,
      "dva_chibi": 1,
      "sombra_comum": 1,
      "rainha_junker_executora": 1,
      "ana_comum": 1,
      "tracer_comum": 1,
      "hanzo_okami": 2,
      "echo_comum": 1,
      "jetpack_cat_comum": 1
    },
    "sets_completos": [
      "deadlock",
      "melee"
    ]
  }
]